{
  "id": 26718,
  "title": "July 25",
  "description": "Double rounds of birthday cakes at our house this week. Happy birthday Dean and Milo!<p>Our main thought about Milo's birthday?  About time!  He's seemed like a six year old for months now.   We started saying we had a 6 and a 8 year old more than a month ago.</p><p>Dean had a hard time deciding how he felt about 37.   It's sorta mid thirties, but also sorta not.  Definitely not as big a deal as graduating from kindergarden.</p><p><strong>Update:</strong> Milo's stats as of July 27:</p><div style=\"margin-left:1em;\">weight: 49 lbs / 22.2 kg</div><div style=\"margin-left:1em;\">height: 47 1/4 inches / 120 cm</div>",
  "keywords": null,
  "summary": "Happy Birthday, Dean and Milo!",
  "pathComponent": "07-25",
  "entityType": "GalleryAlbumItem",
  "creationTimestamp": 1280119706,
  "ownerId": 6,
  "url": "v/2010/07-25/",
  "thumbnail": {
    "id": 26722,
    "width": 100,
    "height": 100,
    "mimeType": "image/jpeg",
    "url": "http://tacocat.com/pictures/d/26722-5/07-25.jpg"
  },
  "children": [
    {
      "id": 26799,
      "title": "To France",
      "description": "The Moses family is moving to France!<p>Now that we're all French citizens and the kids are still young and somewhat portable, we decided to pull up stakes and try la vie française.  At least, for a year.  We're swapping houses with a lovely Parisian family who are coming to live in Berkeley.   The kids will be in French public school when it starts Sept 2. </p><p>The French family also has kids, so we don't even have to bring Legos, video game systems, etc... we're just swapping it all!  Even our cars.</p><p>Milo's a little too young to get the scope of how long we'll be gone, but Felix is keenly aware.  His main beef is that there's no karate dojo in our new neighborhood.  Other than that it's cool.</p><p>Dean and Lucie will be working.</p>",
      "keywords": null,
      "summary": "",
      "pathComponent": "afrance.jpg",
      "entityType": "GalleryPhotoItem",
      "creationTimestamp": 1280207965,
      "ownerId": 6,
      "url": "v/2010/07-25/afrance.jpg.html",
      "thumbnail": {
        "id": 26800,
        "width": 100,
        "height": 100,
        "mimeType": "image/jpeg",
        "url": "http://tacocat.com/pictures/d/26800-5/afrance.jpg"
      },
      "width": 640,
      "height": 380,
      "mimeType": "image/jpeg",
      "size": 113773
    },
    {
      "id": 26719,
      "title": "Lacrosse",
      "description": "Felix and Milo have spent the last two weeks at Cal Youth sports camp.<p>Felix has been playing lacrosse every day.</p>",
      "keywords": null,
      "summary": "",
      "pathComponent": "calyouth1.jpg",
      "entityType": "GalleryPhotoItem",
      "creationTimestamp": 1280119871,
      "ownerId": 6,
      "url": "v/2010/07-25/calyouth1.jpg.html",
      "thumbnail": {
        "id": 26721,
        "width": 100,
        "height": 100,
        "mimeType": "image/jpeg",
        "url": "http://tacocat.com/pictures/d/26721-3/calyouth1.jpg"
      },
      "width": 1024,
      "height": 768,
      "mimeType": "image/jpeg",
      "size": 304209
    },
    {
      "id": 26723,
      "title": "Basketball",
      "description": "And basketball.",
      "keywords": null,
      "summary": "",
      "pathComponent": "calyouth2.jpg",
      "entityType": "GalleryPhotoItem",
      "creationTimestamp": 1280119873,
      "ownerId": 6,
      "url": "v/2010/07-25/calyouth2.jpg.html",
      "thumbnail": {
        "id": 26725,
        "width": 100,
        "height": 100,
        "mimeType": "image/jpeg",
        "url": "http://tacocat.com/pictures/d/26725-5/calyouth2.jpg"
      },
      "width": 1024,
      "height": 768,
      "mimeType": "image/jpeg",
      "size": 287473
    },
    {
      "id": 26726,
      "title": "Dribble",
      "description": "Dribbling with two balls!",
      "keywords": "",
      "summary": "",
      "pathComponent": "calyouth3.jpg",
      "entityType": "GalleryPhotoItem",
      "creationTimestamp": 1280119875,
      "ownerId": 6,
      "url": "v/2010/07-25/calyouth3.jpg.html",
      "thumbnail": {
        "id": 26728,
        "width": 100,
        "height": 100,
        "mimeType": "image/jpeg",
        "url": "http://tacocat.com/pictures/d/26728-3/calyouth3.jpg"
      },
      "width": 1024,
      "height": 768,
      "mimeType": "image/jpeg",
      "size": 209551
    },
    {
      "id": 26729,
      "title": "Sportsman",
      "description": "The days are very full: football, lacrosse, soccer, basketball, swimming plus some light arts and crafts. <p>Felix is loving it and so is Milo. </p>",
      "keywords": null,
      "summary": "",
      "pathComponent": "calyouth4.jpg",
      "entityType": "GalleryPhotoItem",
      "creationTimestamp": 1280119878,
      "ownerId": 6,
      "url": "v/2010/07-25/calyouth4.jpg.html",
      "thumbnail": {
        "id": 26731,
        "width": 100,
        "height": 100,
        "mimeType": "image/jpeg",
        "url": "http://tacocat.com/pictures/d/26731-2/calyouth4.jpg"
      },
      "width": 768,
      "height": 1024,
      "mimeType": "image/jpeg",
      "size": 303101
    },
    {
      "id": 26732,
      "title": "Goalies",
      "description": "August and Felix (wearing August's hat) man the soccer goal.",
      "keywords": null,
      "summary": "",
      "pathComponent": "calyouth5.jpg",
      "entityType": "GalleryPhotoItem",
      "creationTimestamp": 1280119880,
      "ownerId": 6,
      "url": "v/2010/07-25/calyouth5.jpg.html",
      "thumbnail": {
        "id": 26734,
        "width": 100,
        "height": 100,
        "mimeType": "image/jpeg",
        "url": "http://tacocat.com/pictures/d/26734-2/calyouth5.jpg"
      },
      "width": 1024,
      "height": 768,
      "mimeType": "image/jpeg",
      "size": 290951
    },
    {
      "id": 26735,
      "title": "Golden Dragons",
      "description": "Dean and Harriet came on \"Parents' Day\" to observe. <p>Dean got tired of observing and asked to be added to the team. Wish granted! </p>",
      "keywords": null,
      "summary": "",
      "pathComponent": "calyouth6.jpg",
      "entityType": "GalleryPhotoItem",
      "creationTimestamp": 1280119882,
      "ownerId": 6,
      "url": "v/2010/07-25/calyouth6.jpg.html",
      "thumbnail": {
        "id": 26737,
        "width": 100,
        "height": 100,
        "mimeType": "image/jpeg",
        "url": "http://tacocat.com/pictures/d/26737-2/calyouth6.jpg"
      },
      "width": 768,
      "height": 1024,
      "mimeType": "image/jpeg",
      "size": 283091
    },
    {
      "id": 26738,
      "title": "Holding Hands",
      "description": "After Dean played with the Golden Dragons, he remained one of the team. ",
      "keywords": "",
      "summary": "",
      "pathComponent": "calyouth7.jpg",
      "entityType": "GalleryPhotoItem",
      "creationTimestamp": 1280119885,
      "ownerId": 6,
      "url": "v/2010/07-25/calyouth7.jpg.html",
      "thumbnail": {
        "id": 26740,
        "width": 100,
        "height": 100,
        "mimeType": "image/jpeg",
        "url": "http://tacocat.com/pictures/d/26740-3/calyouth7.jpg"
      },
      "width": 1024,
      "height": 768,
      "mimeType": "image/jpeg",
      "size": 269792
    },
    {
      "id": 26741,
      "title": "Dean's 37th",
      "description": "Happy Birthday, Dean!<p>Dean blew really hard and wished for his French to improve.</p>",
      "keywords": null,
      "summary": "",
      "pathComponent": "dean37-1.jpg",
      "entityType": "GalleryPhotoItem",
      "creationTimestamp": 1280119887,
      "ownerId": 6,
      "url": "v/2010/07-25/dean37-1.jpg.html",
      "thumbnail": {
        "id": 26743,
        "width": 100,
        "height": 100,
        "mimeType": "image/jpeg",
        "url": "http://tacocat.com/pictures/d/26743-3/dean37-1.jpg"
      },
      "width": 1024,
      "height": 768,
      "mimeType": "image/jpeg",
      "size": 134766
    },
    {
      "id": 26744,
      "title": "Austin",
      "description": "Austin came over for the birthday supper. ",
      "keywords": "",
      "summary": "",
      "pathComponent": "dean37-2.jpg",
      "entityType": "GalleryPhotoItem",
      "creationTimestamp": 1280119889,
      "ownerId": 6,
      "url": "v/2010/07-25/dean37-2.jpg.html",
      "thumbnail": {
        "id": 26746,
        "width": 100,
        "height": 100,
        "mimeType": "image/jpeg",
        "url": "http://tacocat.com/pictures/d/26746-3/dean37-2.jpg"
      },
      "width": 1024,
      "height": 768,
      "mimeType": "image/jpeg",
      "size": 174277
    },
    {
      "id": 26747,
      "title": "Plane",
      "description": "What's Dean doing, scrambling precariously over City property?",
      "keywords": "",
      "summary": "",
      "pathComponent": "geocache1.jpg",
      "entityType": "GalleryPhotoItem",
      "creationTimestamp": 1280119891,
      "ownerId": 6,
      "url": "v/2010/07-25/geocache1.jpg.html",
      "thumbnail": {
        "id": 26749,
        "width": 100,
        "height": 100,
        "mimeType": "image/jpeg",
        "url": "http://tacocat.com/pictures/d/26749-3/geocache1.jpg"
      },
      "width": 1024,
      "height": 768,
      "mimeType": "image/jpeg",
      "size": 166446
    },
    {
      "id": 26750,
      "title": "Geocache",
      "description": "He is geocaching! This can only mean one thing: Harriet is in town. ",
      "keywords": "",
      "summary": "",
      "pathComponent": "geocache2.jpg",
      "entityType": "GalleryPhotoItem",
      "creationTimestamp": 1280119893,
      "ownerId": 6,
      "url": "v/2010/07-25/geocache2.jpg.html",
      "thumbnail": {
        "id": 26752,
        "width": 100,
        "height": 100,
        "mimeType": "image/jpeg",
        "url": "http://tacocat.com/pictures/d/26752-2/geocache2.jpg"
      },
      "width": 1024,
      "height": 768,
      "mimeType": "image/jpeg",
      "size": 195131
    },
    {
      "id": 26753,
      "title": "Victory!",
      "description": "Are they celebrating finding the cache or the fact that Dean failed to plummet into the bay?",
      "keywords": null,
      "summary": "",
      "pathComponent": "geocache3.jpg",
      "entityType": "GalleryPhotoItem",
      "creationTimestamp": 1280119895,
      "ownerId": 6,
      "url": "v/2010/07-25/geocache3.jpg.html",
      "thumbnail": {
        "id": 26755,
        "width": 100,
        "height": 100,
        "mimeType": "image/jpeg",
        "url": "http://tacocat.com/pictures/d/26755-3/geocache3.jpg"
      },
      "width": 1024,
      "height": 768,
      "mimeType": "image/jpeg",
      "size": 154760
    },
    {
      "id": 26756,
      "title": "Paris Gang",
      "description": "Two other EB families are going to Paris next year. This was our pre-France reunion. Felix, Lucy and Madeleine are in the same grade. We are already making plans to meet in Paris for Madeleine's birthday in September. <p>Felix, Lucy, Milo, Madeleine and her brother Oliver. </p>",
      "keywords": "",
      "summary": "",
      "pathComponent": "helloparis.jpg",
      "entityType": "GalleryPhotoItem",
      "creationTimestamp": 1280119897,
      "ownerId": 6,
      "url": "v/2010/07-25/helloparis.jpg.html",
      "thumbnail": {
        "id": 26758,
        "width": 100,
        "height": 98,
        "mimeType": "image/jpeg",
        "url": "http://tacocat.com/pictures/d/26758-3/helloparis.jpg"
      },
      "width": 1024,
      "height": 680,
      "mimeType": "image/jpeg",
      "size": 190429
    },
    {
      "id": 26759,
      "title": "Balloon",
      "description": "A trip to the balloon store? This can only mean one thing: there's a birthday and Nana's in town.",
      "keywords": null,
      "summary": "",
      "pathComponent": "milo6-01.jpg",
      "entityType": "GalleryPhotoItem",
      "creationTimestamp": 1280119900,
      "ownerId": 6,
      "url": "v/2010/07-25/milo6-01.jpg.html",
      "thumbnail": {
        "id": 26761,
        "width": 100,
        "height": 100,
        "mimeType": "image/jpeg",
        "url": "http://tacocat.com/pictures/d/26761-3/milo6-01.jpg"
      },
      "width": 1024,
      "height": 768,
      "mimeType": "image/jpeg",
      "size": 227003
    },
    {
      "id": 26762,
      "title": "Piplup Cake",
      "description": "Milo requested to have Piplup on his cake. You've never heard of Piplup? Neither had we! He is a Pokemon creature. <p>Milo provided Piplup's Pokemon card as model and Lucie went to work with the icing. </p>",
      "keywords": null,
      "summary": "",
      "pathComponent": "milo6-02.jpg",
      "entityType": "GalleryPhotoItem",
      "creationTimestamp": 1280119902,
      "ownerId": 6,
      "url": "v/2010/07-25/milo6-02.jpg.html",
      "thumbnail": {
        "id": 26764,
        "width": 98,
        "height": 100,
        "mimeType": "image/jpeg",
        "url": "http://tacocat.com/pictures/d/26764-3/milo6-02.jpg"
      },
      "width": 680,
      "height": 1024,
      "mimeType": "image/jpeg",
      "size": 177428
    },
    {
      "id": 26765,
      "title": "Girls",
      "description": "<p>Milo invited an equal number of girls and boys to his party but pretty much only the girls showed up. We didn't hear any complaints from the birthday boy. </p><p>Tea, Eliza, Milo, Romilly, Chloe and Julia. </p>",
      "keywords": null,
      "summary": "",
      "pathComponent": "milo6-03.jpg",
      "entityType": "GalleryPhotoItem",
      "creationTimestamp": 1280119904,
      "ownerId": 6,
      "url": "v/2010/07-25/milo6-03.jpg.html",
      "thumbnail": {
        "id": 26767,
        "width": 100,
        "height": 98,
        "mimeType": "image/jpeg",
        "url": "http://tacocat.com/pictures/d/26767-3/milo6-03.jpg"
      },
      "width": 1024,
      "height": 680,
      "mimeType": "image/jpeg",
      "size": 242943
    },
    {
      "id": 26768,
      "title": "Tickling",
      "description": "Milo knows what's good: being tickled by a gaggle of little girls. ",
      "keywords": "",
      "summary": "",
      "pathComponent": "milo6-04.jpg",
      "entityType": "GalleryPhotoItem",
      "creationTimestamp": 1280119906,
      "ownerId": 6,
      "url": "v/2010/07-25/milo6-04.jpg.html",
      "thumbnail": {
        "id": 26770,
        "width": 100,
        "height": 100,
        "mimeType": "image/jpeg",
        "url": "http://tacocat.com/pictures/d/26770-2/milo6-04.jpg"
      },
      "width": 1024,
      "height": 768,
      "mimeType": "image/jpeg",
      "size": 185062
    },
    {
      "id": 26771,
      "title": "Poison Candy",
      "description": "We played Poison Candy, a game imported from France (Lucie played it at <a href=\"/pictures/v/2010/03-21/france09.jpg.html\">Zoe's birthday party</a> in March). <p>Notice Jack standing on the side, holding his blaster gun. He kept a safe distance from the action... was he afraid of potentially poisonous candy or of cooties? You can't be too safe. </p>",
      "keywords": null,
      "summary": "",
      "pathComponent": "milo6-05.jpg",
      "entityType": "GalleryPhotoItem",
      "creationTimestamp": 1280119908,
      "ownerId": 6,
      "url": "v/2010/07-25/milo6-05.jpg.html",
      "thumbnail": {
        "id": 26773,
        "width": 100,
        "height": 100,
        "mimeType": "image/jpeg",
        "url": "http://tacocat.com/pictures/d/26773-3/milo6-05.jpg"
      },
      "width": 1024,
      "height": 768,
      "mimeType": "image/jpeg",
      "size": 158189
    },
    {
      "id": 26774,
      "title": "Candy",
      "description": "Clara carefully pick a piece of candy from the tray. <p>If you pick the type of candy that the others have decided is poisonous, you DIE.  What's worse, your turn as candy picker ENDS. </p>",
      "keywords": null,
      "summary": "",
      "pathComponent": "milo6-06.jpg",
      "entityType": "GalleryPhotoItem",
      "creationTimestamp": 1280119910,
      "ownerId": 6,
      "url": "v/2010/07-25/milo6-06.jpg.html",
      "thumbnail": {
        "id": 26776,
        "width": 100,
        "height": 98,
        "mimeType": "image/jpeg",
        "url": "http://tacocat.com/pictures/d/26776-3/milo6-06.jpg"
      },
      "width": 1024,
      "height": 680,
      "mimeType": "image/jpeg",
      "size": 253247
    },
    {
      "id": 26777,
      "title": "Cake",
      "description": "Cake time!   <p>A roomful of friends singing Happy Birthday is music to Milo's ears.</p>",
      "keywords": null,
      "summary": "",
      "pathComponent": "milo6-07.jpg",
      "entityType": "GalleryPhotoItem",
      "creationTimestamp": 1280119913,
      "ownerId": 6,
      "url": "v/2010/07-25/milo6-07.jpg.html",
      "thumbnail": {
        "id": 26779,
        "width": 100,
        "height": 98,
        "mimeType": "image/jpeg",
        "url": "http://tacocat.com/pictures/d/26779-3/milo6-07.jpg"
      },
      "width": 1024,
      "height": 680,
      "mimeType": "image/jpeg",
      "size": 172966
    },
    {
      "id": 26780,
      "title": "Wish",
      "description": "Make a wish",
      "keywords": "",
      "summary": "",
      "pathComponent": "milo6-08.jpg",
      "entityType": "GalleryPhotoItem",
      "creationTimestamp": 1280119915,
      "ownerId": 6,
      "url": "v/2010/07-25/milo6-08.jpg.html",
      "thumbnail": {
        "id": 26782,
        "width": 100,
        "height": 100,
        "mimeType": "image/jpeg",
        "url": "http://tacocat.com/pictures/d/26782-5/milo6-08.jpg"
      },
      "width": 1024,
      "height": 680,
      "mimeType": "image/jpeg",
      "size": 167127
    },
    {
      "id": 26783,
      "title": "Blow!",
      "description": "His official first breath as a 6 year old. ",
      "keywords": "",
      "summary": "",
      "pathComponent": "milo6-09.jpg",
      "entityType": "GalleryPhotoItem",
      "creationTimestamp": 1280119917,
      "ownerId": 6,
      "url": "v/2010/07-25/milo6-09.jpg.html",
      "thumbnail": {
        "id": 26785,
        "width": 100,
        "height": 98,
        "mimeType": "image/jpeg",
        "url": "http://tacocat.com/pictures/d/26785-3/milo6-09.jpg"
      },
      "width": 1024,
      "height": 680,
      "mimeType": "image/jpeg",
      "size": 171420
    },
    {
      "id": 26786,
      "title": "Six!",
      "description": "Yes! Milo is 6!",
      "keywords": "",
      "summary": "",
      "pathComponent": "milo6-10.jpg",
      "entityType": "GalleryPhotoItem",
      "creationTimestamp": 1280119919,
      "ownerId": 6,
      "url": "v/2010/07-25/milo6-10.jpg.html",
      "thumbnail": {
        "id": 26788,
        "width": 100,
        "height": 98,
        "mimeType": "image/jpeg",
        "url": "http://tacocat.com/pictures/d/26788-3/milo6-10.jpg"
      },
      "width": 1024,
      "height": 680,
      "mimeType": "image/jpeg",
      "size": 135308
    },
    {
      "id": 26789,
      "title": "Presents",
      "description": "We asked guests to keep presents small so they could accompany us on our upcoming travels.",
      "keywords": null,
      "summary": "",
      "pathComponent": "milo6-11.jpg",
      "entityType": "GalleryPhotoItem",
      "creationTimestamp": 1280119921,
      "ownerId": 6,
      "url": "v/2010/07-25/milo6-11.jpg.html",
      "thumbnail": {
        "id": 26791,
        "width": 100,
        "height": 100,
        "mimeType": "image/jpeg",
        "url": "http://tacocat.com/pictures/d/26791-3/milo6-11.jpg"
      },
      "width": 1024,
      "height": 768,
      "mimeType": "image/jpeg",
      "size": 161341
    },
    {
      "id": 26792,
      "title": "Louisa",
      "description": "Louisa and daughter Julia (not pictured: twin daughter Eliza). ",
      "keywords": "",
      "summary": "",
      "pathComponent": "milo6-12.jpg",
      "entityType": "GalleryPhotoItem",
      "creationTimestamp": 1280119923,
      "ownerId": 6,
      "url": "v/2010/07-25/milo6-12.jpg.html",
      "thumbnail": {
        "id": 26794,
        "width": 100,
        "height": 100,
        "mimeType": "image/jpeg",
        "url": "http://tacocat.com/pictures/d/26794-2/milo6-12.jpg"
      },
      "width": 768,
      "height": 1024,
      "mimeType": "image/jpeg",
      "size": 138328
    },
    {
      "id": 26795,
      "title": "Nana",
      "description": "Nana shares some quiet time with a newly minted six year old.",
      "keywords": null,
      "summary": "",
      "pathComponent": "milo6-13.jpg",
      "entityType": "GalleryPhotoItem",
      "creationTimestamp": 1280119925,
      "ownerId": 6,
      "url": "v/2010/07-25/milo6-13.jpg.html",
      "thumbnail": {
        "id": 26797,
        "width": 100,
        "height": 98,
        "mimeType": "image/jpeg",
        "url": "http://tacocat.com/pictures/d/26797-3/milo6-13.jpg"
      },
      "width": 1024,
      "height": 680,
      "mimeType": "image/jpeg",
      "size": 210506
    }
  ]
}