{
  "id": 53437,
  "title": "February 3",
  "description": "For most of the San Francisco Bay Area, the big event of the weekend was the Super Bowl, where our home team the 49ers competed for the title of best football team in America.<p>However, we had plans for a different bowl game:  we headed up to the Tahoe area and went to the Sugar Bowl resort for some family skiiing.   </p>",
  "keywords": null,
  "summary": "Tahoe",
  "pathComponent": "02-03",
  "entityType": "GalleryAlbumItem",
  "creationTimestamp": 1359958077,
  "ownerId": 6,
  "url": "v/2013/02-03/",
  "thumbnail": {
    "id": 53442,
    "width": 100,
    "height": 100,
    "mimeType": "image/jpeg",
    "url": "http://tacocat.com/pictures/d/53442-4/02-03.jpg"
  },
  "children": [
    {
      "id": 53440,
      "title": "Arrival",
      "description": "Since we took a ski vacation at Christmas, we have ski clothes and snow boots that fit every family member. We're making the most of it!<p>For this trip, we also packed our sled. </p>",
      "keywords": null,
      "summary": "",
      "pathComponent": "clair-tappaan-lodge1.jpg",
      "entityType": "GalleryPhotoItem",
      "creationTimestamp": 1359958139,
      "ownerId": 6,
      "url": "v/2013/02-03/clair-tappaan-lodge1.jpg.html",
      "thumbnail": {
        "id": 53441,
        "width": 100,
        "height": 100,
        "mimeType": "image/jpeg",
        "url": "http://tacocat.com/pictures/d/53441-2/clair-tappaan-lodge1.jpg"
      },
      "width": 1024,
      "height": 768,
      "mimeType": "image/jpeg",
      "size": 199098
    },
    {
      "id": 53443,
      "title": "Clair Tappaan",
      "description": "We stayed at the Clair Tappaan, a lodge run by the Sierra Club. <p>It's a very Berkeley sort of place, where every family is expected to sign up for a chore a day, and the breakfasts and suppers are communal, in a big mess hall.</p><p>It had been over three years since <a href=\"/pictures/v/2010/01-03/clairtapaan01.jpg.html\">our last visit</a> and we were glad to be back. </p>",
      "keywords": null,
      "summary": "",
      "pathComponent": "clair-tappaan-lodge2.jpg",
      "entityType": "GalleryPhotoItem",
      "creationTimestamp": 1359958143,
      "ownerId": 6,
      "url": "v/2013/02-03/clair-tappaan-lodge2.jpg.html",
      "thumbnail": {
        "id": 53444,
        "width": 100,
        "height": 100,
        "mimeType": "image/jpeg",
        "url": "http://tacocat.com/pictures/d/53444-2/clair-tappaan-lodge2.jpg"
      },
      "width": 1024,
      "height": 768,
      "mimeType": "image/jpeg",
      "size": 148094
    },
    {
      "id": 53445,
      "title": "Bunk Beds",
      "description": "Each room has a bunch of bunk beds. We shared our room with another family.",
      "keywords": "",
      "summary": "",
      "pathComponent": "clair-tappaan-lodge3.jpg",
      "entityType": "GalleryPhotoItem",
      "creationTimestamp": 1359958145,
      "ownerId": 6,
      "url": "v/2013/02-03/clair-tappaan-lodge3.jpg.html",
      "thumbnail": {
        "id": 53446,
        "width": 100,
        "height": 100,
        "mimeType": "image/jpeg",
        "url": "http://tacocat.com/pictures/d/53446-2/clair-tappaan-lodge3.jpg"
      },
      "width": 768,
      "height": 1024,
      "mimeType": "image/jpeg",
      "size": 149428
    },
    {
      "id": 53447,
      "title": "Sugar Bowl",
      "description": "This was our first trip to Tahoe where the kids actually went downhill skiing. <p>The last time, three years ago, neither the kids nor Lucie could ski. </p><p>Lucie and the kids learned to ski in La Joue du Loup (in the French Alps) and fine-tuned their skills in Whistler, Canada. </p>",
      "keywords": "",
      "summary": "",
      "pathComponent": "downhill-skiing1.jpg",
      "entityType": "GalleryPhotoItem",
      "creationTimestamp": 1359958148,
      "ownerId": 6,
      "url": "v/2013/02-03/downhill-skiing1.jpg.html",
      "thumbnail": {
        "id": 53448,
        "width": 100,
        "height": 100,
        "mimeType": "image/jpeg",
        "url": "http://tacocat.com/pictures/d/53448-2/downhill-skiing1.jpg"
      },
      "width": 1024,
      "height": 768,
      "mimeType": "image/jpeg",
      "size": 140923
    },
    {
      "id": 53449,
      "title": "Snowboard",
      "description": "Dean prefers snowboarding, but we don't hold that against him.",
      "keywords": "",
      "summary": "",
      "pathComponent": "downhill-skiing2.jpg",
      "entityType": "GalleryPhotoItem",
      "creationTimestamp": 1359958151,
      "ownerId": 6,
      "url": "v/2013/02-03/downhill-skiing2.jpg.html",
      "thumbnail": {
        "id": 53450,
        "width": 100,
        "height": 100,
        "mimeType": "image/jpeg",
        "url": "http://tacocat.com/pictures/d/53450-2/downhill-skiing2.jpg"
      },
      "width": 1024,
      "height": 768,
      "mimeType": "image/jpeg",
      "size": 142465
    },
    {
      "id": 53451,
      "title": "Harriet's Hollow",
      "description": "Our favorite slope at Sugar Bowl: Harriet's Hollow, which we also referred to as the \"Nana trail\". It has some awesome bumps. ",
      "keywords": "",
      "summary": "",
      "pathComponent": "downhill-skiing3.jpg",
      "entityType": "GalleryPhotoItem",
      "creationTimestamp": 1359958153,
      "ownerId": 6,
      "url": "v/2013/02-03/downhill-skiing3.jpg.html",
      "thumbnail": {
        "id": 53452,
        "width": 100,
        "height": 100,
        "mimeType": "image/jpeg",
        "url": "http://tacocat.com/pictures/d/53452-2/downhill-skiing3.jpg"
      },
      "width": 1024,
      "height": 683,
      "mimeType": "image/jpeg",
      "size": 223211
    },
    {
      "id": 53453,
      "title": "Up Top",
      "description": "Lucie and Felix on top of the mountain, contemplating the slightly scary blue slopes they will have to take to reach the bottom. ",
      "keywords": "",
      "summary": "",
      "pathComponent": "downhill-skiing4.jpg",
      "entityType": "GalleryPhotoItem",
      "creationTimestamp": 1359958156,
      "ownerId": 6,
      "url": "v/2013/02-03/downhill-skiing4.jpg.html",
      "thumbnail": {
        "id": 53454,
        "width": 100,
        "height": 100,
        "mimeType": "image/jpeg",
        "url": "http://tacocat.com/pictures/d/53454-2/downhill-skiing4.jpg"
      },
      "width": 1024,
      "height": 768,
      "mimeType": "image/jpeg",
      "size": 111331
    },
    {
      "id": 53455,
      "title": "Down Low",
      "description": "Milo, are you okay? <p>Don't worry, he slipped down in slow motion while we were studying the map. Nothing got hurt, not even his ego. </p>",
      "keywords": "",
      "summary": "",
      "pathComponent": "downhill-skiing5.jpg",
      "entityType": "GalleryPhotoItem",
      "creationTimestamp": 1359958158,
      "ownerId": 6,
      "url": "v/2013/02-03/downhill-skiing5.jpg.html",
      "thumbnail": {
        "id": 53456,
        "width": 100,
        "height": 100,
        "mimeType": "image/jpeg",
        "url": "http://tacocat.com/pictures/d/53456-2/downhill-skiing5.jpg"
      },
      "width": 1024,
      "height": 768,
      "mimeType": "image/jpeg",
      "size": 104006
    },
    {
      "id": 53457,
      "title": "Lucie",
      "description": "Let's just say that Lucie won't be competing in the next winter olympics.",
      "keywords": "",
      "summary": "",
      "pathComponent": "downhill-skiing6.jpg",
      "entityType": "GalleryPhotoItem",
      "creationTimestamp": 1359958160,
      "ownerId": 6,
      "url": "v/2013/02-03/downhill-skiing6.jpg.html",
      "thumbnail": {
        "id": 53458,
        "width": 100,
        "height": 100,
        "mimeType": "image/jpeg",
        "url": "http://tacocat.com/pictures/d/53458-2/downhill-skiing6.jpg"
      },
      "width": 1024,
      "height": 768,
      "mimeType": "image/jpeg",
      "size": 126541
    },
    {
      "id": 53459,
      "title": "Butt",
      "description": "Enough said. ",
      "keywords": "",
      "summary": "",
      "pathComponent": "downhill-skiing7.jpg",
      "entityType": "GalleryPhotoItem",
      "creationTimestamp": 1359958162,
      "ownerId": 6,
      "url": "v/2013/02-03/downhill-skiing7.jpg.html",
      "thumbnail": {
        "id": 53460,
        "width": 100,
        "height": 100,
        "mimeType": "image/jpeg",
        "url": "http://tacocat.com/pictures/d/53460-2/downhill-skiing7.jpg"
      },
      "width": 1024,
      "height": 768,
      "mimeType": "image/jpeg",
      "size": 209312
    },
    {
      "id": 53461,
      "title": "Downhill",
      "description": "To be fair, she can ski down a slope without falling (mostly). She just doesn't like to go fast. Dean and the kids often had to wait for her. <p>The kids are still at a level where green slopes are just right. This is the sweet spot when all of us can ski together. In another couple of years, they will leave their mom in a cloud of white powdery dust.</p>",
      "keywords": "",
      "summary": "",
      "pathComponent": "downhill-skiing8.jpg",
      "entityType": "GalleryPhotoItem",
      "creationTimestamp": 1359958164,
      "ownerId": 6,
      "url": "v/2013/02-03/downhill-skiing8.jpg.html",
      "thumbnail": {
        "id": 53462,
        "width": 100,
        "height": 100,
        "mimeType": "image/jpeg",
        "url": "http://tacocat.com/pictures/d/53462-2/downhill-skiing8.jpg"
      },
      "width": 1024,
      "height": 768,
      "mimeType": "image/jpeg",
      "size": 72487
    },
    {
      "id": 53463,
      "title": "Fort",
      "description": "As per our tradition when visiting Clair Tappaan, the kids worked on building a snow fort with underground tunnels. Some other kids had started one before them and they added to it. ",
      "keywords": "",
      "summary": "",
      "pathComponent": "fort1.jpg",
      "entityType": "GalleryPhotoItem",
      "creationTimestamp": 1359958166,
      "ownerId": 6,
      "url": "v/2013/02-03/fort1.jpg.html",
      "thumbnail": {
        "id": 53464,
        "width": 100,
        "height": 100,
        "mimeType": "image/jpeg",
        "url": "http://tacocat.com/pictures/d/53464-2/fort1.jpg"
      },
      "width": 1024,
      "height": 768,
      "mimeType": "image/jpeg",
      "size": 141043
    },
    {
      "id": 53465,
      "title": "Igloo",
      "description": "Felix built an igloo on top of the main entrance. <p>It must have been a couple of weeks since the last serious snow fall. The snow was very compact and hard to work with. </p>",
      "keywords": "",
      "summary": "",
      "pathComponent": "fort2.jpg",
      "entityType": "GalleryPhotoItem",
      "creationTimestamp": 1359958168,
      "ownerId": 6,
      "url": "v/2013/02-03/fort2.jpg.html",
      "thumbnail": {
        "id": 53466,
        "width": 100,
        "height": 100,
        "mimeType": "image/jpeg",
        "url": "http://tacocat.com/pictures/d/53466-2/fort2.jpg"
      },
      "width": 1024,
      "height": 768,
      "mimeType": "image/jpeg",
      "size": 142261
    },
    {
      "id": 53467,
      "title": "Well",
      "description": "Three little kids in the well under the igloo. <p>One of the best things about Clair Tappaan is that you always meet new friends. </p>",
      "keywords": null,
      "summary": "",
      "pathComponent": "fort3.jpg",
      "entityType": "GalleryPhotoItem",
      "creationTimestamp": 1359958170,
      "ownerId": 6,
      "url": "v/2013/02-03/fort3.jpg.html",
      "thumbnail": {
        "id": 53468,
        "width": 100,
        "height": 100,
        "mimeType": "image/jpeg",
        "url": "http://tacocat.com/pictures/d/53468-2/fort3.jpg"
      },
      "width": 1024,
      "height": 768,
      "mimeType": "image/jpeg",
      "size": 83844
    },
    {
      "id": 53469,
      "title": "Hike",
      "description": "The compact snow also meant that we were able to take a long hike in the area around the lodge. The last time we came, we needed cross country skis to explore the same trail. ",
      "keywords": "",
      "summary": "",
      "pathComponent": "hike.jpg",
      "entityType": "GalleryPhotoItem",
      "creationTimestamp": 1359958172,
      "ownerId": 6,
      "url": "v/2013/02-03/hike.jpg.html",
      "thumbnail": {
        "id": 53470,
        "width": 100,
        "height": 100,
        "mimeType": "image/jpeg",
        "url": "http://tacocat.com/pictures/d/53470-2/hike.jpg"
      },
      "width": 1024,
      "height": 768,
      "mimeType": "image/jpeg",
      "size": 238765
    },
    {
      "id": 53471,
      "title": "Sledding",
      "description": "Last but not least, the packed snow made for an extra fast sledding hill.",
      "keywords": "",
      "summary": "",
      "pathComponent": "sledding1.jpg",
      "entityType": "GalleryPhotoItem",
      "creationTimestamp": 1359958174,
      "ownerId": 6,
      "url": "v/2013/02-03/sledding1.jpg.html",
      "thumbnail": {
        "id": 53472,
        "width": 100,
        "height": 100,
        "mimeType": "image/jpeg",
        "url": "http://tacocat.com/pictures/d/53472-2/sledding1.jpg"
      },
      "width": 1024,
      "height": 768,
      "mimeType": "image/jpeg",
      "size": 112893
    },
    {
      "id": 53473,
      "title": "Wooosh",
      "description": "Wooosh",
      "keywords": "",
      "summary": "",
      "pathComponent": "sledding2.jpg",
      "entityType": "GalleryPhotoItem",
      "creationTimestamp": 1359958175,
      "ownerId": 6,
      "url": "v/2013/02-03/sledding2.jpg.html",
      "thumbnail": {
        "id": 53474,
        "width": 100,
        "height": 100,
        "mimeType": "image/jpeg",
        "url": "http://tacocat.com/pictures/d/53474-2/sledding2.jpg"
      },
      "width": 1024,
      "height": 768,
      "mimeType": "image/jpeg",
      "size": 123249
    },
    {
      "id": 53475,
      "title": "Crash",
      "description": "Crash",
      "keywords": "",
      "summary": "",
      "pathComponent": "sledding3.jpg",
      "entityType": "GalleryPhotoItem",
      "creationTimestamp": 1359958177,
      "ownerId": 6,
      "url": "v/2013/02-03/sledding3.jpg.html",
      "thumbnail": {
        "id": 53476,
        "width": 100,
        "height": 100,
        "mimeType": "image/jpeg",
        "url": "http://tacocat.com/pictures/d/53476-2/sledding3.jpg"
      },
      "width": 1024,
      "height": 768,
      "mimeType": "image/jpeg",
      "size": 177121
    },
    {
      "id": 53477,
      "title": "All Good",
      "description": "I'm good, you?",
      "keywords": null,
      "summary": "",
      "pathComponent": "sledding4.jpg",
      "entityType": "GalleryPhotoItem",
      "creationTimestamp": 1359958179,
      "ownerId": 6,
      "url": "v/2013/02-03/sledding4.jpg.html",
      "thumbnail": {
        "id": 53478,
        "width": 100,
        "height": 100,
        "mimeType": "image/jpeg",
        "url": "http://tacocat.com/pictures/d/53478-2/sledding4.jpg"
      },
      "width": 1024,
      "height": 768,
      "mimeType": "image/jpeg",
      "size": 157010
    },
    {
      "id": 53479,
      "title": "Again!",
      "description": "Come on Dad, let's get up the hill and do it again!",
      "keywords": null,
      "summary": "",
      "pathComponent": "sledding5.jpg",
      "entityType": "GalleryPhotoItem",
      "creationTimestamp": 1359958181,
      "ownerId": 6,
      "url": "v/2013/02-03/sledding5.jpg.html",
      "thumbnail": {
        "id": 53480,
        "width": 100,
        "height": 100,
        "mimeType": "image/jpeg",
        "url": "http://tacocat.com/pictures/d/53480-4/sledding5.jpg"
      },
      "width": 1024,
      "height": 768,
      "mimeType": "image/jpeg",
      "size": 130515
    },
    {
      "id": 53481,
      "title": "Felix",
      "description": "We brought our own sled but it turns out we didn't really need to. There were plenty of sleds to borrow. The kids diligently tried out every model. ",
      "keywords": "",
      "summary": "",
      "pathComponent": "sledding6.jpg",
      "entityType": "GalleryPhotoItem",
      "creationTimestamp": 1359958183,
      "ownerId": 6,
      "url": "v/2013/02-03/sledding6.jpg.html",
      "thumbnail": {
        "id": 53482,
        "width": 100,
        "height": 100,
        "mimeType": "image/jpeg",
        "url": "http://tacocat.com/pictures/d/53482-2/sledding6.jpg"
      },
      "width": 1024,
      "height": 768,
      "mimeType": "image/jpeg",
      "size": 125843
    },
    {
      "id": 53483,
      "title": "Fast",
      "description": "Some sled go faster than others. Some sled are easier to steer than others. The two qualities rarely go together. ",
      "keywords": "",
      "summary": "",
      "pathComponent": "sledding7.jpg",
      "entityType": "GalleryPhotoItem",
      "creationTimestamp": 1359958185,
      "ownerId": 6,
      "url": "v/2013/02-03/sledding7.jpg.html",
      "thumbnail": {
        "id": 53484,
        "width": 100,
        "height": 100,
        "mimeType": "image/jpeg",
        "url": "http://tacocat.com/pictures/d/53484-2/sledding7.jpg"
      },
      "width": 1024,
      "height": 768,
      "mimeType": "image/jpeg",
      "size": 141765
    },
    {
      "id": 53485,
      "title": "Air",
      "description": "Catching some air. ",
      "keywords": "",
      "summary": "",
      "pathComponent": "sledding8.jpg",
      "entityType": "GalleryPhotoItem",
      "creationTimestamp": 1359958187,
      "ownerId": 6,
      "url": "v/2013/02-03/sledding8.jpg.html",
      "thumbnail": {
        "id": 53486,
        "width": 100,
        "height": 100,
        "mimeType": "image/jpeg",
        "url": "http://tacocat.com/pictures/d/53486-2/sledding8.jpg"
      },
      "width": 1024,
      "height": 683,
      "mimeType": "image/jpeg",
      "size": 157320
    },
    {
      "id": 53487,
      "title": "Super Bowl",
      "description": "We made it back to Berkeley in time to catch the Super Bowl on Sunday. Go niners!<p>Dean tried explaining to Lucie the rules of the game.  We clarified the difference between a first down and a touchdown, that was helpful.</p>",
      "keywords": null,
      "summary": "",
      "pathComponent": "superbowl1.jpg",
      "entityType": "GalleryPhotoItem",
      "creationTimestamp": 1359958189,
      "ownerId": 6,
      "url": "v/2013/02-03/superbowl1.jpg.html",
      "thumbnail": {
        "id": 53488,
        "width": 100,
        "height": 98,
        "mimeType": "image/jpeg",
        "url": "http://tacocat.com/pictures/d/53488-2/superbowl1.jpg"
      },
      "width": 1024,
      "height": 680,
      "mimeType": "image/jpeg",
      "size": 227228
    },
    {
      "id": 53489,
      "title": "Lost",
      "description": "It was a very exciting game but sadly the 49ers lost in the final seconds.",
      "keywords": null,
      "summary": "",
      "pathComponent": "superbowl2.jpg",
      "entityType": "GalleryPhotoItem",
      "creationTimestamp": 1359958190,
      "ownerId": 6,
      "url": "v/2013/02-03/superbowl2.jpg.html",
      "thumbnail": {
        "id": 53490,
        "width": 100,
        "height": 98,
        "mimeType": "image/jpeg",
        "url": "http://tacocat.com/pictures/d/53490-2/superbowl2.jpg"
      },
      "width": 1024,
      "height": 680,
      "mimeType": "image/jpeg",
      "size": 225766
    }
  ]
}