{
  "id": 38060,
  "title": "November 20",
  "description": "For the last few weeks, Felix has been working on his first ever big homework assignment, a book report.  He selected a book from the Akiko series and has been drawing a comic book adaptation of one of the scenes. <p>We are pleased to publish it here in exclusivity.</p>",
  "keywords": null,
  "summary": "Akiko comics",
  "pathComponent": "11-20",
  "entityType": "GalleryAlbumItem",
  "creationTimestamp": 1321854481,
  "ownerId": 6,
  "url": "v/2011/11-20/",
  "thumbnail": {
    "id": 38066,
    "width": 100,
    "height": 100,
    "mimeType": "image/jpeg",
    "url": "http://tacocat.com/pictures/d/38066-5/11-20.jpg"
  },
  "children": [
    {
      "id": 38063,
      "title": "Bay Bridge",
      "description": "Strolling on the beach at the end of Crissy Field, waiting for 3:00 pm. ",
      "keywords": "",
      "summary": "",
      "pathComponent": "beach1.jpg",
      "entityType": "GalleryPhotoItem",
      "creationTimestamp": 1321854588,
      "ownerId": 6,
      "url": "v/2011/11-20/beach1.jpg.html",
      "thumbnail": {
        "id": 38065,
        "width": 100,
        "height": 100,
        "mimeType": "image/jpeg",
        "url": "http://tacocat.com/pictures/d/38065-3/beach1.jpg"
      },
      "width": 1024,
      "height": 768,
      "mimeType": "image/jpeg",
      "size": 142468
    },
    {
      "id": 38067,
      "title": "Sandcastle",
      "description": "Nice wet sand from the rain the previous day. Let's enjoy it quick before the rain forecast for tomorrow!",
      "keywords": "",
      "summary": "",
      "pathComponent": "beach2.jpg",
      "entityType": "GalleryPhotoItem",
      "creationTimestamp": 1321854593,
      "ownerId": 6,
      "url": "v/2011/11-20/beach2.jpg.html",
      "thumbnail": {
        "id": 38069,
        "width": 100,
        "height": 100,
        "mimeType": "image/jpeg",
        "url": "http://tacocat.com/pictures/d/38069-3/beach2.jpg"
      },
      "width": 1024,
      "height": 768,
      "mimeType": "image/jpeg",
      "size": 204614
    },
    {
      "id": 38070,
      "title": "House of Air",
      "description": "3:00 pm! Time to head to the House of Air. <p>This place is awesome. It opened while we were in France. Basically, it's a whole lot of trampolines assembled together. Bounce bounce!</p>",
      "keywords": "",
      "summary": "",
      "pathComponent": "house-of-air1.jpg",
      "entityType": "GalleryPhotoItem",
      "creationTimestamp": 1321854596,
      "ownerId": 6,
      "url": "v/2011/11-20/house-of-air1.jpg.html",
      "thumbnail": {
        "id": 38072,
        "width": 100,
        "height": 100,
        "mimeType": "image/jpeg",
        "url": "http://tacocat.com/pictures/d/38072-3/house-of-air1.jpg"
      },
      "width": 1024,
      "height": 768,
      "mimeType": "image/jpeg",
      "size": 168771
    },
    {
      "id": 38073,
      "title": "Nate",
      "description": "See that blurry kid jumping in the foreground? That's Nathaniel. He had the fine idea of celebrating his 10th birthday at the House of Air. Thanks for inviting us, Nate. ",
      "keywords": "",
      "summary": "",
      "pathComponent": "house-of-air2.jpg",
      "entityType": "GalleryPhotoItem",
      "creationTimestamp": 1321854600,
      "ownerId": 6,
      "url": "v/2011/11-20/house-of-air2.jpg.html",
      "thumbnail": {
        "id": 38075,
        "width": 100,
        "height": 100,
        "mimeType": "image/jpeg",
        "url": "http://tacocat.com/pictures/d/38075-3/house-of-air2.jpg"
      },
      "width": 1024,
      "height": 768,
      "mimeType": "image/jpeg",
      "size": 164664
    },
    {
      "id": 38076,
      "title": "Second Generation",
      "description": "The parents used to go to Burning Man together, now the sons hang out together and swapped Minecraft tips. <p>Felix, Milo, Nathaniel and Lex</p>",
      "keywords": "",
      "summary": "",
      "pathComponent": "house-of-air3.jpg",
      "entityType": "GalleryPhotoItem",
      "creationTimestamp": 1321854602,
      "ownerId": 6,
      "url": "v/2011/11-20/house-of-air3.jpg.html",
      "thumbnail": {
        "id": 38078,
        "width": 100,
        "height": 100,
        "mimeType": "image/jpeg",
        "url": "http://tacocat.com/pictures/d/38078-3/house-of-air3.jpg"
      },
      "width": 1024,
      "height": 768,
      "mimeType": "image/jpeg",
      "size": 154344
    },
    {
      "id": 38079,
      "title": "Dads",
      "description": "In fact, the parents are also swapping Minecraft tips these days. <p>Steve (Nathaniel's dad) and Taylor (Lex's dad) discuss the finer points of the Minecraft server Taylor set up</p>",
      "keywords": null,
      "summary": "",
      "pathComponent": "house-of-air4.jpg",
      "entityType": "GalleryPhotoItem",
      "creationTimestamp": 1321854605,
      "ownerId": 6,
      "url": "v/2011/11-20/house-of-air4.jpg.html",
      "thumbnail": {
        "id": 38081,
        "width": 100,
        "height": 100,
        "mimeType": "image/jpeg",
        "url": "http://tacocat.com/pictures/d/38081-3/house-of-air4.jpg"
      },
      "width": 1024,
      "height": 768,
      "mimeType": "image/jpeg",
      "size": 183099
    },
    {
      "id": 38082,
      "title": "Cooking",
      "description": "Ony 5 more cooking days until Thanksgiving! <p>We will be spending Turkey Day at the Joyces. Milo's contribution: homemade Nutella ice-cream. </p>",
      "keywords": null,
      "summary": "",
      "pathComponent": "nutella-icecream1.jpg",
      "entityType": "GalleryPhotoItem",
      "creationTimestamp": 1321854608,
      "ownerId": 6,
      "url": "v/2011/11-20/nutella-icecream1.jpg.html",
      "thumbnail": {
        "id": 38084,
        "width": 100,
        "height": 98,
        "mimeType": "image/jpeg",
        "url": "http://tacocat.com/pictures/d/38084-3/nutella-icecream1.jpg"
      },
      "width": 1024,
      "height": 680,
      "mimeType": "image/jpeg",
      "size": 211602
    },
    {
      "id": 38085,
      "title": "Stirring",
      "description": "Swelling with pride for being trusted at the stove top. ",
      "keywords": "",
      "summary": "",
      "pathComponent": "nutella-icecream2.jpg",
      "entityType": "GalleryPhotoItem",
      "creationTimestamp": 1321854611,
      "ownerId": 6,
      "url": "v/2011/11-20/nutella-icecream2.jpg.html",
      "thumbnail": {
        "id": 38087,
        "width": 100,
        "height": 98,
        "mimeType": "image/jpeg",
        "url": "http://tacocat.com/pictures/d/38087-3/nutella-icecream2.jpg"
      },
      "width": 1024,
      "height": 680,
      "mimeType": "image/jpeg",
      "size": 222724
    },
    {
      "id": 38088,
      "title": "Thickening",
      "description": "The Nutella is melting nicely into the custard. The cook is bouncing to the music. Gorillaz, I believe.",
      "keywords": null,
      "summary": "",
      "pathComponent": "nutella-icecream3.jpg",
      "entityType": "GalleryPhotoItem",
      "creationTimestamp": 1321854613,
      "ownerId": 6,
      "url": "v/2011/11-20/nutella-icecream3.jpg.html",
      "thumbnail": {
        "id": 38090,
        "width": 100,
        "height": 98,
        "mimeType": "image/jpeg",
        "url": "http://tacocat.com/pictures/d/38090-3/nutella-icecream3.jpg"
      },
      "width": 1024,
      "height": 680,
      "mimeType": "image/jpeg",
      "size": 216025
    },
    {
      "id": 38091,
      "title": "Akiko p.1",
      "description": "Akiko is a girl from Earth who goes on intergalactic adventures. Felix has avidly read all six books in the series. This is a comic book version of chapter 21 and 22 from book 6. ",
      "keywords": "",
      "summary": "",
      "pathComponent": "report-akiko1.jpg",
      "entityType": "GalleryPhotoItem",
      "creationTimestamp": 1321854616,
      "ownerId": 6,
      "url": "v/2011/11-20/report-akiko1.jpg.html",
      "thumbnail": {
        "id": 38093,
        "width": 100,
        "height": 100,
        "mimeType": "image/jpeg",
        "url": "http://tacocat.com/pictures/d/38093-5/report-akiko1.jpg"
      },
      "width": 792,
      "height": 1024,
      "mimeType": "image/jpeg",
      "size": 77142
    },
    {
      "id": 38094,
      "title": "Akiko p.2",
      "description": "For some panels, Felix asked for help to figure out how to draw a particular body position. Lucie make little sketches as models. ",
      "keywords": "",
      "summary": "",
      "pathComponent": "report-akiko2.jpg",
      "entityType": "GalleryPhotoItem",
      "creationTimestamp": 1321854618,
      "ownerId": 6,
      "url": "v/2011/11-20/report-akiko2.jpg.html",
      "thumbnail": {
        "id": 38096,
        "width": 99,
        "height": 100,
        "mimeType": "image/jpeg",
        "url": "http://tacocat.com/pictures/d/38096-3/report-akiko2.jpg"
      },
      "width": 793,
      "height": 1024,
      "mimeType": "image/jpeg",
      "size": 121434
    },
    {
      "id": 38097,
      "title": "Akiko p.3",
      "description": "Felix and Lucie also flipped though comic books together to study how comic book artists divide the page, use type as a graphical elements and other subtleties. ",
      "keywords": "",
      "summary": "",
      "pathComponent": "report-akiko3.jpg",
      "entityType": "GalleryPhotoItem",
      "creationTimestamp": 1321854619,
      "ownerId": 6,
      "url": "v/2011/11-20/report-akiko3.jpg.html",
      "thumbnail": {
        "id": 38099,
        "width": 99,
        "height": 100,
        "mimeType": "image/jpeg",
        "url": "http://tacocat.com/pictures/d/38099-3/report-akiko3.jpg"
      },
      "width": 793,
      "height": 1024,
      "mimeType": "image/jpeg",
      "size": 154378
    },
    {
      "id": 38100,
      "title": "Akiko p.4",
      "description": "In case you are having a hard time following the action: Akiko is pursuing the evil robot Thirgen through the air. Thirgen has stolen Gax, a friendly robot friend of Akiko because Thirgen wants to use Gax's body as spare parts for his own body.",
      "keywords": "",
      "summary": "",
      "pathComponent": "report-akiko4.jpg",
      "entityType": "GalleryPhotoItem",
      "creationTimestamp": 1321854622,
      "ownerId": 6,
      "url": "v/2011/11-20/report-akiko4.jpg.html",
      "thumbnail": {
        "id": 38102,
        "width": 99,
        "height": 100,
        "mimeType": "image/jpeg",
        "url": "http://tacocat.com/pictures/d/38102-3/report-akiko4.jpg"
      },
      "width": 793,
      "height": 1024,
      "mimeType": "image/jpeg",
      "size": 150878
    },
    {
      "id": 38103,
      "title": "Akiko p.5",
      "description": "Felix worked on one page a day each weekend, for 4 weekends in a row. He usually does not have homework on weekends so this was quite a feat.<p>We believe Felix is the only one in his class who will be turning in his book report as a comic book. Each student got to pick the format. Some are making drawings, others are putting together a play...</p>",
      "keywords": null,
      "summary": "",
      "pathComponent": "report-akiko5.jpg",
      "entityType": "GalleryPhotoItem",
      "creationTimestamp": 1321854623,
      "ownerId": 6,
      "url": "v/2011/11-20/report-akiko5.jpg.html",
      "thumbnail": {
        "id": 38105,
        "width": 99,
        "height": 100,
        "mimeType": "image/jpeg",
        "url": "http://tacocat.com/pictures/d/38105-3/report-akiko5.jpg"
      },
      "width": 793,
      "height": 1024,
      "mimeType": "image/jpeg",
      "size": 100876
    },
    {
      "id": 38106,
      "title": "Akiko p.6",
      "description": "Transcribing the dialogue from the book to the comic book was probably the most taxing part for Felix. ",
      "keywords": "",
      "summary": "",
      "pathComponent": "report-akiko6.jpg",
      "entityType": "GalleryPhotoItem",
      "creationTimestamp": 1321854626,
      "ownerId": 6,
      "url": "v/2011/11-20/report-akiko6.jpg.html",
      "thumbnail": {
        "id": 38108,
        "width": 99,
        "height": 100,
        "mimeType": "image/jpeg",
        "url": "http://tacocat.com/pictures/d/38108-3/report-akiko6.jpg"
      },
      "width": 792,
      "height": 1024,
      "mimeType": "image/jpeg",
      "size": 122562
    },
    {
      "id": 38109,
      "title": "Akiko p.7",
      "description": "Oh no! Akiko has been cornered by Thirgen. <p>Have no fear. Poog, another friend of Akiko's, is about to save her from certain doom by stealthily handing her a hurpleskap, an alien sea creature that disolves metal on touch. </p>",
      "keywords": "",
      "summary": "",
      "pathComponent": "report-akiko7.jpg",
      "entityType": "GalleryPhotoItem",
      "creationTimestamp": 1321854629,
      "ownerId": 6,
      "url": "v/2011/11-20/report-akiko7.jpg.html",
      "thumbnail": {
        "id": 38111,
        "width": 99,
        "height": 100,
        "mimeType": "image/jpeg",
        "url": "http://tacocat.com/pictures/d/38111-3/report-akiko7.jpg"
      },
      "width": 791,
      "height": 1024,
      "mimeType": "image/jpeg",
      "size": 137903
    },
    {
      "id": 38112,
      "title": "Akiko p.8",
      "description": "Victory! Akiko has defeated Thirgen by throwing the hurpleskap in his face!",
      "keywords": "",
      "summary": "",
      "pathComponent": "report-akiko8.jpg",
      "entityType": "GalleryPhotoItem",
      "creationTimestamp": 1321854632,
      "ownerId": 6,
      "url": "v/2011/11-20/report-akiko8.jpg.html",
      "thumbnail": {
        "id": 38114,
        "width": 99,
        "height": 100,
        "mimeType": "image/jpeg",
        "url": "http://tacocat.com/pictures/d/38114-3/report-akiko8.jpg"
      },
      "width": 793,
      "height": 1024,
      "mimeType": "image/jpeg",
      "size": 103905
    }
  ]
}