{
  "id": 64327,
  "title": "December 14",
  "description": "The day Felix turned into a teenager had panache and dramatic flair. The entire Bay Area declared a state of emergency. Schools were closed for the day. Office workers were urged to work from home.<p>All the <em>sturm und drang</em> was not, however, because of one boy's ascent into teenagerdom.  We had the Storm of the Decade!</p> <p>If you watched the news, the worst storm in recent history wreaked havoc with roads and caused mud slides. From where WE stood, it was downright cozy. Everybody was at home, either working or playing.  We spent the day indoors listening to the rain pelt the windows. Felix slowly opened his presents from breakfast to evening. Lucie took breaks from work to cook yummy birthday-worthy desserts. </p><p>The best part was that we hadn't been expecting to spend the day together. The storm felt like a gift from the skies to celebrate our birthday boy.</p>",
  "keywords": null,
  "summary": "Felix is a teenager!",
  "pathComponent": "12-14",
  "entityType": "GalleryAlbumItem",
  "creationTimestamp": 1418587423,
  "ownerId": 6,
  "url": "v/2014/12-14/",
  "thumbnail": {
    "id": 64330,
    "width": 100,
    "height": 98,
    "mimeType": "image/jpeg",
    "url": "http://tacocat.com/pictures/d/64330-4/12-14.jpg"
  },
  "children": [
    {
      "id": 64328,
      "title": "Breakfast",
      "description": "<strong>Thursday December 11, 9:00 am:</strong>  instead of being at school, Felix gets ready to open birthday presents at home.",
      "keywords": null,
      "summary": "",
      "pathComponent": "birthday1.jpg",
      "entityType": "GalleryPhotoItem",
      "creationTimestamp": 1418591222,
      "ownerId": 6,
      "url": "v/2014/12-14/birthday1.jpg.html",
      "thumbnail": {
        "id": 64329,
        "width": 100,
        "height": 98,
        "mimeType": "image/jpeg",
        "url": "http://tacocat.com/pictures/d/64329-2/birthday1.jpg"
      },
      "width": 1024,
      "height": 680,
      "mimeType": "image/jpeg",
      "size": 138253
    },
    {
      "id": 64331,
      "title": "Presents",
      "description": "The day's menu:<ul><li>Present from Milo before breakfast</li><li>Presents from parents after breakfast</li><li>Presents from Babushka after lunch *</li><li>Presents from Nana after snack</li></ul><p>* The only time Felix opened the front door on his extra wet birthday was to accept a parcel from France, brought mid-morning by a mailman wearing a heavy rain jacket. </p>",
      "keywords": null,
      "summary": "",
      "pathComponent": "birthday2.jpg",
      "entityType": "GalleryPhotoItem",
      "creationTimestamp": 1418591225,
      "ownerId": 6,
      "url": "v/2014/12-14/birthday2.jpg.html",
      "thumbnail": {
        "id": 64332,
        "width": 100,
        "height": 98,
        "mimeType": "image/jpeg",
        "url": "http://tacocat.com/pictures/d/64332-2/birthday2.jpg"
      },
      "width": 1024,
      "height": 680,
      "mimeType": "image/jpeg",
      "size": 117295
    },
    {
      "id": 64333,
      "title": "Don't Starve",
      "description": "The day was spent playing with brand new Lego sets and with <i>Don't Starve</i>, a video game. ",
      "keywords": "",
      "summary": "",
      "pathComponent": "birthday3.jpg",
      "entityType": "GalleryPhotoItem",
      "creationTimestamp": 1418591228,
      "ownerId": 6,
      "url": "v/2014/12-14/birthday3.jpg.html",
      "thumbnail": {
        "id": 64334,
        "width": 100,
        "height": 98,
        "mimeType": "image/jpeg",
        "url": "http://tacocat.com/pictures/d/64334-2/birthday3.jpg"
      },
      "width": 1024,
      "height": 680,
      "mimeType": "image/jpeg",
      "size": 91889
    },
    {
      "id": 64335,
      "title": "Growth",
      "description": "Felix grew about 3.5 inches this year (almost 9 centimeters). He is almost 5' 6\". <p>However, he weighs <em>exactly</em> what he did a year ago. His body proportions are changing. He is getting slimmer and more broad-shouldered. </p>",
      "keywords": null,
      "summary": "",
      "pathComponent": "birthday4.jpg",
      "entityType": "GalleryPhotoItem",
      "creationTimestamp": 1418591231,
      "ownerId": 6,
      "url": "v/2014/12-14/birthday4.jpg.html",
      "thumbnail": {
        "id": 64336,
        "width": 100,
        "height": 98,
        "mimeType": "image/jpeg",
        "url": "http://tacocat.com/pictures/d/64336-2/birthday4.jpg"
      },
      "width": 1024,
      "height": 680,
      "mimeType": "image/jpeg",
      "size": 80611
    },
    {
      "id": 64337,
      "title": "Caramel",
      "description": "What's a mom's to do when a celebration dessert is unexpectedly called for, and it's too wet to go grocery shopping?  <p>Answer: Turn a cup of white sugar into caramel sauce. </p>",
      "keywords": "",
      "summary": "",
      "pathComponent": "caramel1.jpg",
      "entityType": "GalleryPhotoItem",
      "creationTimestamp": 1418591235,
      "ownerId": 6,
      "url": "v/2014/12-14/caramel1.jpg.html",
      "thumbnail": {
        "id": 64338,
        "width": 100,
        "height": 98,
        "mimeType": "image/jpeg",
        "url": "http://tacocat.com/pictures/d/64338-2/caramel1.jpg"
      },
      "width": 1024,
      "height": 680,
      "mimeType": "image/jpeg",
      "size": 136305
    },
    {
      "id": 64339,
      "title": "Chemistry",
      "description": "Making caramel feels like playing with a chemistry set. It changes colors! It bubbles! Solids turn to liquid and back to solid!",
      "keywords": null,
      "summary": "",
      "pathComponent": "caramel2.jpg",
      "entityType": "GalleryPhotoItem",
      "creationTimestamp": 1418591238,
      "ownerId": 6,
      "url": "v/2014/12-14/caramel2.jpg.html",
      "thumbnail": {
        "id": 64340,
        "width": 100,
        "height": 98,
        "mimeType": "image/jpeg",
        "url": "http://tacocat.com/pictures/d/64340-2/caramel2.jpg"
      },
      "width": 1024,
      "height": 680,
      "mimeType": "image/jpeg",
      "size": 106063
    },
    {
      "id": 64341,
      "title": "Dessert",
      "description": "Homemade caramel sauce enlivens the birthday lunch. ",
      "keywords": "",
      "summary": "",
      "pathComponent": "caramel3.jpg",
      "entityType": "GalleryPhotoItem",
      "creationTimestamp": 1418591241,
      "ownerId": 6,
      "url": "v/2014/12-14/caramel3.jpg.html",
      "thumbnail": {
        "id": 64342,
        "width": 100,
        "height": 98,
        "mimeType": "image/jpeg",
        "url": "http://tacocat.com/pictures/d/64342-2/caramel3.jpg"
      },
      "width": 1024,
      "height": 680,
      "mimeType": "image/jpeg",
      "size": 106021
    },
    {
      "id": 64395,
      "title": "Damage",
      "description": "How bad of a rain storm was it, anyway? The media called it \"stormageddon\" and broadcast cars stranded on flooded roads. <p>But honestly, it felt like a lot of fuss about nothing much. It was just heavy rain. With the drought of the last three years, we could us a few more stormageddons! As much as we enjoyed staying home for this one, we hope schools and offices won't shut down every time the rain gets heavy. </p>",
      "keywords": null,
      "summary": "",
      "pathComponent": "damage.jpg",
      "entityType": "GalleryPhotoItem",
      "creationTimestamp": 1418592174,
      "ownerId": 6,
      "url": "v/2014/12-14/damage.jpg.html",
      "thumbnail": {
        "id": 64396,
        "width": 100,
        "height": 100,
        "mimeType": "image/jpeg",
        "url": "http://tacocat.com/pictures/d/64396-2/damage.jpg"
      },
      "width": 400,
      "height": 400,
      "mimeType": "image/jpeg",
      "size": 130139
    },
    {
      "id": 64343,
      "title": "Iles Flottantes",
      "description": "For the birthday dinner we had Safeway lasagna (Felix's favorite) and homemade îles flottantes.",
      "keywords": null,
      "summary": "",
      "pathComponent": "iles-flottantes1.jpg",
      "entityType": "GalleryPhotoItem",
      "creationTimestamp": 1418591243,
      "ownerId": 6,
      "url": "v/2014/12-14/iles-flottantes1.jpg.html",
      "thumbnail": {
        "id": 64344,
        "width": 100,
        "height": 98,
        "mimeType": "image/jpeg",
        "url": "http://tacocat.com/pictures/d/64344-2/iles-flottantes1.jpg"
      },
      "width": 1024,
      "height": 680,
      "mimeType": "image/jpeg",
      "size": 30503
    },
    {
      "id": 64345,
      "title": "Happy",
      "description": "Happy Birthday, Felix!",
      "keywords": "",
      "summary": "",
      "pathComponent": "iles-flottantes2.jpg",
      "entityType": "GalleryPhotoItem",
      "creationTimestamp": 1418591246,
      "ownerId": 6,
      "url": "v/2014/12-14/iles-flottantes2.jpg.html",
      "thumbnail": {
        "id": 64346,
        "width": 100,
        "height": 98,
        "mimeType": "image/jpeg",
        "url": "http://tacocat.com/pictures/d/64346-2/iles-flottantes2.jpg"
      },
      "width": 1024,
      "height": 680,
      "mimeType": "image/jpeg",
      "size": 94794
    },
    {
      "id": 64347,
      "title": "Dim Sum",
      "description": "Saturday.  Dim sum at Yang Sing.",
      "keywords": null,
      "summary": "",
      "pathComponent": "sing-yang.jpg",
      "entityType": "GalleryPhotoItem",
      "creationTimestamp": 1418591258,
      "ownerId": 6,
      "url": "v/2014/12-14/sing-yang.jpg.html",
      "thumbnail": {
        "id": 64348,
        "width": 98,
        "height": 100,
        "mimeType": "image/jpeg",
        "url": "http://tacocat.com/pictures/d/64348-6/sing-yang.jpg"
      },
      "width": 1024,
      "height": 682,
      "mimeType": "image/jpeg",
      "size": 70921
    },
    {
      "id": 64349,
      "title": "Ice Skating",
      "description": "Ice skating on Justin Herman Plaza in San Francisco.",
      "keywords": "",
      "summary": "",
      "pathComponent": "skating1.jpg",
      "entityType": "GalleryPhotoItem",
      "creationTimestamp": 1418591262,
      "ownerId": 6,
      "url": "v/2014/12-14/skating1.jpg.html",
      "thumbnail": {
        "id": 64350,
        "width": 100,
        "height": 98,
        "mimeType": "image/jpeg",
        "url": "http://tacocat.com/pictures/d/64350-2/skating1.jpg"
      },
      "width": 1024,
      "height": 682,
      "mimeType": "image/jpeg",
      "size": 134082
    },
    {
      "id": 64351,
      "title": "Gloves",
      "description": "Lucie wore ski-grade heavy gloves, just in case. ",
      "keywords": "",
      "summary": "",
      "pathComponent": "skating2.jpg",
      "entityType": "GalleryPhotoItem",
      "creationTimestamp": 1418591265,
      "ownerId": 6,
      "url": "v/2014/12-14/skating2.jpg.html",
      "thumbnail": {
        "id": 64352,
        "width": 100,
        "height": 98,
        "mimeType": "image/jpeg",
        "url": "http://tacocat.com/pictures/d/64352-2/skating2.jpg"
      },
      "width": 1024,
      "height": 682,
      "mimeType": "image/jpeg",
      "size": 124128
    },
    {
      "id": 64353,
      "title": "Skating",
      "description": "Dean remembered how to ice skate right away. <p>Felix and Lucie were very very slow and awkward at first but got back into the groove of it soon enough. </p>",
      "keywords": "",
      "summary": "",
      "pathComponent": "skating3.jpg",
      "entityType": "GalleryPhotoItem",
      "creationTimestamp": 1418591269,
      "ownerId": 6,
      "url": "v/2014/12-14/skating3.jpg.html",
      "thumbnail": {
        "id": 64354,
        "width": 100,
        "height": 98,
        "mimeType": "image/jpeg",
        "url": "http://tacocat.com/pictures/d/64354-2/skating3.jpg"
      },
      "width": 1024,
      "height": 682,
      "mimeType": "image/jpeg",
      "size": 121223
    },
    {
      "id": 64355,
      "title": "Wild",
      "description": "Milo was a high speed action-tragicomedy movie. He skittered and flailed over the ice at respectable speed but with no technique whatsoever. He suffered more tumbles than all the rest of us put together. By far. <p>Dean tried to impart some of his limited skating wisdom, but Milo inherited someone's thick head about that sort of thing.</p>",
      "keywords": null,
      "summary": "",
      "pathComponent": "skating4.jpg",
      "entityType": "GalleryPhotoItem",
      "creationTimestamp": 1418591272,
      "ownerId": 6,
      "url": "v/2014/12-14/skating4.jpg.html",
      "thumbnail": {
        "id": 64356,
        "width": 100,
        "height": 98,
        "mimeType": "image/jpeg",
        "url": "http://tacocat.com/pictures/d/64356-2/skating4.jpg"
      },
      "width": 1024,
      "height": 682,
      "mimeType": "image/jpeg",
      "size": 89779
    },
    {
      "id": 64357,
      "title": "Family",
      "description": "Eventually, our ice skating adventure ended when Milo twisted his ankle. ",
      "keywords": "",
      "summary": "",
      "pathComponent": "skating5.jpg",
      "entityType": "GalleryPhotoItem",
      "creationTimestamp": 1418591276,
      "ownerId": 6,
      "url": "v/2014/12-14/skating5.jpg.html",
      "thumbnail": {
        "id": 64358,
        "width": 100,
        "height": 98,
        "mimeType": "image/jpeg",
        "url": "http://tacocat.com/pictures/d/64358-2/skating5.jpg"
      },
      "width": 1024,
      "height": 682,
      "mimeType": "image/jpeg",
      "size": 118562
    },
    {
      "id": 64359,
      "title": "Ride",
      "description": "Milo's getting too heavy for Lucie to carry far, but Felix is picking up the slack.  Because of his ankle, he gave Milo a piggy-back ride back to the car.<p>Don't worry: Milo's ankle was as good a new by the next day. </p>",
      "keywords": null,
      "summary": "",
      "pathComponent": "skating6.jpg",
      "entityType": "GalleryPhotoItem",
      "creationTimestamp": 1418591280,
      "ownerId": 6,
      "url": "v/2014/12-14/skating6.jpg.html",
      "thumbnail": {
        "id": 64360,
        "width": 100,
        "height": 98,
        "mimeType": "image/jpeg",
        "url": "http://tacocat.com/pictures/d/64360-2/skating6.jpg"
      },
      "width": 1024,
      "height": 682,
      "mimeType": "image/jpeg",
      "size": 177171
    }
  ]
}